{
    "extension": {
        "name": "com.castsoftware.nosqljava",
        "href": "AIP/extensions/com.castsoftware.nosqljava"
    },
    "name": "1.2.3-funcrel",
    "href": "AIP/extensions/com.castsoftware.nosqljava/versions/1.2.3-funcrel",
    "publishedTime": "2021-06-02T09:10:25+0000",
    "qualityModel": true,
    "transactionsConfiguration": true,
    "transactionsConfigurationCRC": 3692135552,
    "metaModelCRC": 3403462754,
    "rulesCRC": 442851839,
    "qualityRules": {
        "name": "Quality Rules in numeric ID order",
        "href": "AIP/extensions/com.castsoftware.nosqljava/versions/1.2.3-funcrel/quality-rules"
    }
}
