{
    "extension": {
        "name": "com.castsoftware.nosqljava",
        "href": "AIP/extensions/com.castsoftware.nosqljava"
    },
    "name": "1.9.4-funcrel",
    "href": "AIP/extensions/com.castsoftware.nosqljava/versions/1.9.4-funcrel",
    "publishedTime": "2025-12-12T10:07:21+0000",
    "qualityModel": true,
    "transactionsConfiguration": true,
    "transactionsConfigurationCRC": 2189436285,
    "metaModelCRC": 474349495,
    "rulesCRC": 4008990548,
    "qualityRules": {
        "name": "Quality Rules in numeric ID order",
        "href": "AIP/extensions/com.castsoftware.nosqljava/versions/1.9.4-funcrel/quality-rules"
    }
}
